diffaid/__init__.py
diffaid/cli.py
diffaid/git.py
diffaid/models.py
diffaid/ai/__init__.py
diffaid/ai/base.py
diffaid/ai/gemini.py
diffaid-0.2.1.dist-info/licenses/LICENSE
diffaid-0.2.1.dist-info/METADATA
diffaid-0.2.1.dist-info/WHEEL
diffaid-0.2.1.dist-info/entry_points.txt
diffaid-0.2.1.dist-info/top_level.txt
diffaid-0.2.1.dist-info/RECORD
