Metadata-Version: 2.4
Name: diffaid
Version: 0.2.1
Summary: AI-assisted git diff review CLI
Author-email: Nathan Towsley <natetowsley@gmail.com>
License: MIT License
Project-URL: Repository, https://github.com/natetowsley/diffaid
Keywords: git,diff,ai,code-review,cli,gemini
Classifier: Development Status :: 3 - Alpha
Classifier: Intended Audience :: Developers
Classifier: License :: OSI Approved :: MIT License
Classifier: Programming Language :: Python :: 3
Classifier: Programming Language :: Python :: 3.10
Classifier: Programming Language :: Python :: 3.11
Classifier: Programming Language :: Python :: 3.12
Classifier: Topic :: Software Development :: Quality Assurance
Classifier: Topic :: Software Development :: Version Control :: Git
Classifier: Environment :: Console
Requires-Python: >=3.10
License-File: LICENSE
Requires-Dist: typer>=0.12
Requires-Dist: google-genai>=0.3.0
Requires-Dist: pydantic>=2.0
Requires-Dist: rich>=13.0
Requires-Dist: python-dotenv
Provides-Extra: dev
Requires-Dist: pytest>=7.0; extra == "dev"
Requires-Dist: pytest-cov>=4.0; extra == "dev"
Requires-Dist: pytest-mock>=3.0; extra == "dev"
Dynamic: license-file
